jarvis_module1/__init__.py
jarvis_module1-0.0.1.dist-info/LICENCE
jarvis_module1-0.0.1.dist-info/METADATA
jarvis_module1-0.0.1.dist-info/WHEEL
jarvis_module1-0.0.1.dist-info/top_level.txt
jarvis_module1-0.0.1.dist-info/RECORD
